abacum/__init__.py
abacum/ai/__init__.py
abacum/ai/mcp/__init__.py
abacum/ai/mcp/__main__.py
abacum/ai/mcp/api.py
abacum/ai/mcp/data_processing.py
abacum/ai/mcp/resources.py
abacum/ai/mcp/server.py
abacum/ai/mcp/tools.py
abacum/ai/mcp/validators.py
abacum_mcp_server-0.1.7.dist-info/licenses/LICENSE
abacum_mcp_server-0.1.7.dist-info/METADATA
abacum_mcp_server-0.1.7.dist-info/WHEEL
abacum_mcp_server-0.1.7.dist-info/entry_points.txt
abacum_mcp_server-0.1.7.dist-info/top_level.txt
abacum_mcp_server-0.1.7.dist-info/RECORD
