Metadata-Version: 2.4
Name: abacum-mcp-server
Version: 0.1.7
Summary: Abacum MCP Server
Author-email: Abacum <engineering@abacum.ai>
License: # Proprietary Software License for Abacum MCP Server
Project-URL: Homepage, https://abacum.ai
Classifier: Programming Language :: Python :: 3
Classifier: License :: Other/Proprietary License
Classifier: Operating System :: OS Independent
Classifier: Topic :: Scientific/Engineering :: Interface Engine/Protocol Translator
Requires-Python: >=3.8
License-File: LICENSE
Requires-Dist: fastmcp
Requires-Dist: httpx
Requires-Dist: pandas
Dynamic: license-file
